prlps_speller/__init__.py
prlps_speller-0.0.1.dist-info/LICENSE.txt
prlps_speller-0.0.1.dist-info/METADATA
prlps_speller-0.0.1.dist-info/WHEEL
prlps_speller-0.0.1.dist-info/top_level.txt
prlps_speller-0.0.1.dist-info/RECORD
