Metadata-Version: 2.2
Name: prlps_speller
Version: 0.0.1
Summary: асинхронный спеллер с использованием API Yandex Speller
Home-page: https://github.com/gniloyprolaps/prlps_speller
Author: prolapser
License: LICENSE.txt
Classifier: Development Status :: 4 - Beta
Classifier: Intended Audience :: Developers
Classifier: License :: OSI Approved :: MIT License
Classifier: Operating System :: OS Independent
Requires-Python: >=3.10
License-File: LICENSE.txt
Requires-Dist: httpx
Dynamic: author
Dynamic: classifier
Dynamic: description
Dynamic: description-content-type
Dynamic: home-page
Dynamic: license
Dynamic: requires-dist
Dynamic: requires-python
Dynamic: summary
